{
  "data": {
    "success": true,
    "user_profile": {
      "type": "instagram",
      "user_id": "12281817",
      "username": "kyliejenner",
      "handle": "kyliejenner",
      "url": "https://www.instagram.com/kyliejenner/",
      "picture": "https://upload.wikimedia.org/wikipedia/commons/thumb/6/6e/Kylie_Jenner1_%28cropped%29.png/330px-Kylie_Jenner1_%28cropped%29.png",
      "fullname": "Kylie",
      "is_verified": true,
      "followers": 396278529,
      "engagements": 2288558,
      "engagement_rate": 0.005775124899587986,
      "avg_likes": 2288558,
      "avg_comments": 18308,
      "avg_views": 0,
      "posts_count": 1200
    }
  }
}